betsapi3/__init__.py
betsapi3/base_client.py
betsapi3/bet365.py
betsapi3/utils.py
betsapi3-0.1.2.dist-info/WHEEL
betsapi3-0.1.2.dist-info/METADATA
betsapi3-0.1.2.dist-info/RECORD
