Metadata-Version: 2.1
Name: betsapi3
Version: 0.1.2
Summary: Unofficial BetsAPI wrapper for Python3
Home-page: https://github.com/tavkhelidzeluka/betsapi3-python
Author: tavkhelidzeluka
Author-email: tavkhelidzeluka@gmail.com
Requires-Python: >=3.10,<4.0
Classifier: Programming Language :: Python :: 3
Classifier: Programming Language :: Python :: 3.10
Requires-Dist: requests (>=2.28.0,<3.0.0)
Project-URL: Repository, https://github.com/tavkhelidzeluka/betsapi3-python
